rentCalculations/__init__.py
rentCalculations/rentCalculations.py
rentUtility-0.1.0.dist-info/LICENSE
rentUtility-0.1.0.dist-info/METADATA
rentUtility-0.1.0.dist-info/WHEEL
rentUtility-0.1.0.dist-info/top_level.txt
rentUtility-0.1.0.dist-info/RECORD
